[{"timestamp": "2008-07-31 21:00", "programmed": 34803, "forecast": 34461}, {"timestamp": "2008-07-31 21:10", "programmed": 34803, "forecast": 34454}, {"timestamp": "2008-07-31 21:20", "programmed": 34803, "forecast": 34488}, {"timestamp": "2008-07-31 21:30", "programmed": 34803, "forecast": 34562}, {"timestamp": "2008-07-31 21:40", "programmed": 34803, "forecast": 34676}, {"timestamp": "2008-07-31 21:50", "programmed": 34803, "forecast": 34831}, {"timestamp": "2008-07-31 22:00", "programmed": 34714, "forecast": 35026}, {"timestamp": "2008-07-31 22:10", "programmed": 34714, "forecast": 35175}, {"timestamp": "2008-07-31 22:20", "programmed": 34714, "forecast": 35189}, {"timestamp": "2008-07-31 22:30", "programmed": 34714, "forecast": 35068}, {"timestamp": "2008-07-31 22:40", "programmed": 34714, "forecast": 34814}, {"timestamp": "2008-07-31 22:50", "programmed": 34714, "forecast": 34425}, {"timestamp": "2008-07-31 23:00", "programmed": 32125, "forecast": 33900}, {"timestamp": "2008-07-31 23:10", "programmed": 32125, "forecast": 33333}, {"timestamp": "2008-07-31 23:20", "programmed": 32125, "forecast": 32814}, {"timestamp": "2008-07-31 23:30", "programmed": 32125, "forecast": 32341}, {"timestamp": "2008-07-31 23:40", "programmed": 32125, "forecast": 31916}, {"timestamp": "2008-07-31 23:50", "programmed": 32125, "forecast": 31538}, {"timestamp": "2008-08-01 00:00", "programmed": 29761, "forecast": 31207}, {"timestamp": "2008-08-01 00:10", "programmed": 29761, "forecast": 30887}, {"timestamp": "2008-08-01 00:20", "programmed": 29761, "forecast": 30544}, {"timestamp": "2008-08-01 00:30", "programmed": 29761, "forecast": 30176}, {"timestamp": "2008-08-01 00:40", "programmed": 29761, "forecast": 29783}, {"timestamp": "2008-08-01 00:50", "programmed": 29761, "forecast": 29366}, {"timestamp": "2008-08-01 01:00", "programmed": 27362, "forecast": 28923}, {"timestamp": "2008-08-01 01:10", "programmed": 27362, "forecast": 28486}, {"timestamp": "2008-08-01 01:20", "programmed": 27362, "forecast": 28081}, {"timestamp": "2008-08-01 01:30", "programmed": 27362, "forecast": 27709}, {"timestamp": "2008-08-01 01:40", "programmed": 27362, "forecast": 27369}, {"timestamp": "2008-08-01 01:50", "programmed": 27362, "forecast": 27063}, {"timestamp": "2008-08-01 02:00", "programmed": 25679, "forecast": 26788}, {"timestamp": "2008-08-01 02:10", "programmed": 25679, "forecast": 26540}, {"timestamp": "2008-08-01 02:20", "programmed": 25679, "forecast": 26310}, {"timestamp": "2008-08-01 02:30", "programmed": 25679, "forecast": 26098}, {"timestamp": "2008-08-01 02:40", "programmed": 25679, "forecast": 25905}, {"timestamp": "2008-08-01 02:50", "programmed": 25679, "forecast": 25730}, {"timestamp": "2008-08-01 03:00", "programmed": 24939, "forecast": 25572}, {"timestamp": "2008-08-01 03:10", "programmed": 24939, "forecast": 25434}, {"timestamp": "2008-08-01 03:20", "programmed": 24939, "forecast": 25314}, {"timestamp": "2008-08-01 03:30", "programmed": 24939, "forecast": 25213}, {"timestamp": "2008-08-01 03:40", "programmed": 24939, "forecast": 25131}, {"timestamp": "2008-08-01 03:50", "programmed": 24939, "forecast": 25068}, {"timestamp": "2008-08-01 04:00", "programmed": 24868, "forecast": 25024}, {"timestamp": "2008-08-01 04:10", "programmed": 24868, "forecast": 24990}, {"timestamp": "2008-08-01 04:20", "programmed": 24868, "forecast": 24958}, {"timestamp": "2008-08-01 04:30", "programmed": 24868, "forecast": 24928}, {"timestamp": "2008-08-01 04:40", "programmed": 24868, "forecast": 24899}, {"timestamp": "2008-08-01 04:50", "programmed": 24868, "forecast": 24873}, {"timestamp": "2008-08-01 05:00", "programmed": 24826, "forecast": 24848}, {"timestamp": "2008-08-01 05:10", "programmed": 24826, "forecast": 24848}, {"timestamp": "2008-08-01 05:20", "programmed": 24826, "forecast": 24895}, {"timestamp": "2008-08-01 05:30", "programmed": 24826, "forecast": 24989}, {"timestamp": "2008-08-01 05:40", "programmed": 24826, "forecast": 25131}, {"timestamp": "2008-08-01 05:50", "programmed": 24826, "forecast": 25320}, {"timestamp": "2008-08-01 06:00", "programmed": 26634, "forecast": 25557}, {"timestamp": "2008-08-01 06:10", "programmed": 26634, "forecast": 25832}, {"timestamp": "2008-08-01 06:20", "programmed": 26634, "forecast": 26139}, {"timestamp": "2008-08-01 06:30", "programmed": 26634, "forecast": 26478}, {"timestamp": "2008-08-01 06:40", "programmed": 26634, "forecast": 26848}, {"timestamp": "2008-08-01 06:50", "programmed": 26634, "forecast": 27249}, {"timestamp": "2008-08-01 07:00", "programmed": 28507, "forecast": 27683}, {"timestamp": "2008-08-01 07:10", "programmed": 28507, "forecast": 28137}, {"timestamp": "2008-08-01 07:20", "programmed": 28507, "forecast": 28601}, {"timestamp": "2008-08-01 07:30", "programmed": 28507, "forecast": 29075}, {"timestamp": "2008-08-01 07:40", "programmed": 28507, "forecast": 29559}, {"timestamp": "2008-08-01 07:50", "programmed": 28507, "forecast": 30053}, {"timestamp": "2008-08-01 08:00", "programmed": 31473, "forecast": 30558}, {"timestamp": "2008-08-01 08:10", "programmed": 31473, "forecast": 31062}, {"timestamp": "2008-08-01 08:20", "programmed": 31473, "forecast": 31555}, {"timestamp": "2008-08-01 08:30", "programmed": 31473, "forecast": 32039}, {"timestamp": "2008-08-01 08:40", "programmed": 31473, "forecast": 32513}, {"timestamp": "2008-08-01 08:50", "programmed": 31473, "forecast": 32976}, {"timestamp": "2008-08-01 09:00", "programmed": 34351, "forecast": 33430}, {"timestamp": "2008-08-01 09:10", "programmed": 34351, "forecast": 33869}, {"timestamp": "2008-08-01 09:20", "programmed": 34351, "forecast": 34289}, {"timestamp": "2008-08-01 09:30", "programmed": 34351, "forecast": 34690}, {"timestamp": "2008-08-01 09:40", "programmed": 34351, "forecast": 35071}, {"timestamp": "2008-08-01 09:50", "programmed": 34351, "forecast": 35434}, {"timestamp": "2008-08-01 10:00", "programmed": 36446, "forecast": 35778}, {"timestamp": "2008-08-01 10:10", "programmed": 36446, "forecast": 36091}, {"timestamp": "2008-08-01 10:20", "programmed": 36446, "forecast": 36360}, {"timestamp": "2008-08-01 10:30", "programmed": 36446, "forecast": 36587}, {"timestamp": "2008-08-01 10:40", "programmed": 36446, "forecast": 36770}, {"timestamp": "2008-08-01 10:50", "programmed": 36446, "forecast": 36911}, {"timestamp": "2008-08-01 11:00", "programmed": 37413, "forecast": 37008}, {"timestamp": "2008-08-01 11:10", "programmed": 37413, "forecast": 37088}, {"timestamp": "2008-08-01 11:20", "programmed": 37413, "forecast": 37175}, {"timestamp": "2008-08-01 11:30", "programmed": 37413, "forecast": 37270}, {"timestamp": "2008-08-01 11:40", "programmed": 37413, "forecast": 37374}, {"timestamp": "2008-08-01 11:50", "programmed": 37413, "forecast": 37485}, {"timestamp": "2008-08-01 12:00", "programmed": 37986, "forecast": 37605}, {"timestamp": "2008-08-01 12:10", "programmed": 37986, "forecast": 37725}, {"timestamp": "2008-08-01 12:20", "programmed": 37986, "forecast": 37838}, {"timestamp": "2008-08-01 12:30", "programmed": 37986, "forecast": 37946}, {"timestamp": "2008-08-01 12:40", "programmed": 37986, "forecast": 38047}, {"timestamp": "2008-08-01 12:50", "programmed": 37986, "forecast": 38142}, {"timestamp": "2008-08-01 13:00", "programmed": 38368, "forecast": 38231}, {"timestamp": "2008-08-01 13:10", "programmed": 38368, "forecast": 38278}, {"timestamp": "2008-08-01 13:20", "programmed": 38368, "forecast": 38248}, {"timestamp": "2008-08-01 13:30", "programmed": 38368, "forecast": 38140}, {"timestamp": "2008-08-01 13:40", "programmed": 38368, "forecast": 37956}, {"timestamp": "2008-08-01 13:50", "programmed": 38368, "forecast": 37695}, {"timestamp": "2008-08-01 14:00", "programmed": 36934, "forecast": 37355}, {"timestamp": "2008-08-01 14:10", "programmed": 36934, "forecast": 36998}, {"timestamp": "2008-08-01 14:20", "programmed": 36934, "forecast": 36680}, {"timestamp": "2008-08-01 14:30", "programmed": 36934, "forecast": 36403}, {"timestamp": "2008-08-01 14:40", "programmed": 36934, "forecast": 36167}, {"timestamp": "2008-08-01 14:50", "programmed": 36934, "forecast": 35970}, {"timestamp": "2008-08-01 15:00", "programmed": 36093, "forecast": 35814}, {"timestamp": "2008-08-01 15:10", "programmed": 36093, "forecast": 35700}, {"timestamp": "2008-08-01 15:20", "programmed": 36093, "forecast": 35630}, {"timestamp": "2008-08-01 15:30", "programmed": 36093, "forecast": 35604}, {"timestamp": "2008-08-01 15:40", "programmed": 36093, "forecast": 35623}, {"timestamp": "2008-08-01 15:50", "programmed": 36093, "forecast": 35686}, {"timestamp": "2008-08-01 16:00", "programmed": 35713, "forecast": 35793}, {"timestamp": "2008-08-01 16:10", "programmed": 35713, "forecast": 35916}, {"timestamp": "2008-08-01 16:20", "programmed": 35713, "forecast": 36025}, {"timestamp": "2008-08-01 16:30", "programmed": 35713, "forecast": 36121}, {"timestamp": "2008-08-01 16:40", "programmed": 35713, "forecast": 36203}, {"timestamp": "2008-08-01 16:50", "programmed": 35713, "forecast": 36272}, {"timestamp": "2008-08-01 17:00", "programmed": 35913, "forecast": 36327}, {"timestamp": "2008-08-01 17:10", "programmed": 35913, "forecast": 36364}, {"timestamp": "2008-08-01 17:20", "programmed": 35913, "forecast": 36376}, {"timestamp": "2008-08-01 17:30", "programmed": 35913, "forecast": 36363}, {"timestamp": "2008-08-01 17:40", "programmed": 35913, "forecast": 36325}, {"timestamp": "2008-08-01 17:50", "programmed": 35913, "forecast": 36263}, {"timestamp": "2008-08-01 18:00", "programmed": 36091, "forecast": 36175}, {"timestamp": "2008-08-01 18:10", "programmed": 36091, "forecast": 36078}, {"timestamp": "2008-08-01 18:20", "programmed": 36091, "forecast": 35987}, {"timestamp": "2008-08-01 18:30", "programmed": 36091, "forecast": 35902}, {"timestamp": "2008-08-01 18:40", "programmed": 36091, "forecast": 35822}, {"timestamp": "2008-08-01 18:50", "programmed": 36091, "forecast": 35748}, {"timestamp": "2008-08-01 19:00", "programmed": 35303, "forecast": 35680}, {"timestamp": "2008-08-01 19:10", "programmed": 35303, "forecast": 35600}, {"timestamp": "2008-08-01 19:20", "programmed": 35303, "forecast": 35489}, {"timestamp": "2008-08-01 19:30", "programmed": 35303, "forecast": 35349}, {"timestamp": "2008-08-01 19:40", "programmed": 35303, "forecast": 35180}, {"timestamp": "2008-08-01 19:50", "programmed": 35303, "forecast": 34980}, {"timestamp": "2008-08-01 20:00", "programmed": 34027, "forecast": 34750}, {"timestamp": "2008-08-01 20:10", "programmed": 34027, "forecast": 34523}, {"timestamp": "2008-08-01 20:20", "programmed": 34027, "forecast": 34332}, {"timestamp": "2008-08-01 20:30", "programmed": 34027, "forecast": 34175}, {"timestamp": "2008-08-01 20:40", "programmed": 34027, "forecast": 34053}, {"timestamp": "2008-08-01 20:50", "programmed": 34027, "forecast": 33967}, {"timestamp": "2008-08-01 21:00", "programmed": 33963, "forecast": 33916}, {"timestamp": "2008-08-01 21:10", "programmed": 33963, "forecast": 33896}, {"timestamp": "2008-08-01 21:20", "programmed": 33963, "forecast": 33904}, {"timestamp": "2008-08-01 21:30", "programmed": 33963, "forecast": 33941}, {"timestamp": "2008-08-01 21:40", "programmed": 33963, "forecast": 34007}, {"timestamp": "2008-08-01 21:50", "programmed": 33963, "forecast": 34102}, {"timestamp": "2008-08-01 22:00", "programmed": 34059, "forecast": 34226}, {"timestamp": "2008-08-01 22:10", "programmed": 34059, "forecast": 34309}, {"timestamp": "2008-08-01 22:20", "programmed": 34059, "forecast": 34283}, {"timestamp": "2008-08-01 22:30", "programmed": 34059, "forecast": 34146}, {"timestamp": "2008-08-01 22:40", "programmed": 34059, "forecast": 33901}, {"timestamp": "2008-08-01 22:50", "programmed": 34059, "forecast": 33545}, {"timestamp": "2008-08-01 23:00", "programmed": 31280, "forecast": 33078}, {"timestamp": "2008-08-01 23:10", "programmed": 31280, "forecast": 32587}, {"timestamp": "2008-08-01 23:20", "programmed": 31280, "forecast": 32155}, {"timestamp": "2008-08-01 23:30", "programmed": 31280, "forecast": 31781}, {"timestamp": "2008-08-01 23:40", "programmed": 31280, "forecast": 31466}, {"timestamp": "2008-08-01 23:50", "programmed": 31280, "forecast": 31209}, {"timestamp": "2008-08-02 00:00", "programmed": 29592, "forecast": 31010}, {"timestamp": "2008-08-02 00:10", "programmed": 29592, "forecast": 30825}, {"timestamp": "2008-08-02 00:20", "programmed": 29592, "forecast": 30606}, {"timestamp": "2008-08-02 00:30", "programmed": 29592, "forecast": 30353}, {"timestamp": "2008-08-02 00:40", "programmed": 29592, "forecast": 30066}, {"timestamp": "2008-08-02 00:50", "programmed": 29592, "forecast": 29745}, {"timestamp": "2008-08-02 01:00", "programmed": 27442, "forecast": 29390}, {"timestamp": "2008-08-02 01:10", "programmed": 27442, "forecast": 29011}, {"timestamp": "2008-08-02 01:20", "programmed": 27442, "forecast": 28617}, {"timestamp": "2008-08-02 01:30", "programmed": 27442, "forecast": 28208}, {"timestamp": "2008-08-02 01:40", "programmed": 27442, "forecast": 27785}, {"timestamp": "2008-08-02 01:50", "programmed": 27442, "forecast": 27346}, {"timestamp": "2008-08-02 02:00", "programmed": 25878, "forecast": 26891}, {"timestamp": "2008-08-02 02:10", "programmed": 25878, "forecast": 26457}, {"timestamp": "2008-08-02 02:20", "programmed": 25878, "forecast": 26075}, {"timestamp": "2008-08-02 02:30", "programmed": 25878, "forecast": 25747}, {"timestamp": "2008-08-02 02:40", "programmed": 25878, "forecast": 25472}, {"timestamp": "2008-08-02 02:50", "programmed": 25878, "forecast": 25250}, {"timestamp": "2008-08-02 03:00", "programmed": 24497, "forecast": 25081}, {"timestamp": "2008-08-02 03:10", "programmed": 24497, "forecast": 24941}, {"timestamp": "2008-08-02 03:20", "programmed": 24497, "forecast": 24804}, {"timestamp": "2008-08-02 03:30", "programmed": 24497, "forecast": 24670}, {"timestamp": "2008-08-02 03:40", "programmed": 24497, "forecast": 24541}, {"timestamp": "2008-08-02 03:50", "programmed": 24497, "forecast": 24414}]