[{"timestamp": "2009-07-09 21:00", "programmed": 32089, "forecast": 31987}, {"timestamp": "2009-07-09 21:10", "programmed": 32089, "forecast": 31965}, {"timestamp": "2009-07-09 21:20", "programmed": 32089, "forecast": 31980}, {"timestamp": "2009-07-09 21:30", "programmed": 32089, "forecast": 32031}, {"timestamp": "2009-07-09 21:40", "programmed": 32089, "forecast": 32118}, {"timestamp": "2009-07-09 21:50", "programmed": 32089, "forecast": 32242}, {"timestamp": "2009-07-09 22:00", "programmed": 31963, "forecast": 32403}, {"timestamp": "2009-07-09 22:10", "programmed": 31963, "forecast": 32523}, {"timestamp": "2009-07-09 22:20", "programmed": 31963, "forecast": 32526}, {"timestamp": "2009-07-09 22:30", "programmed": 31963, "forecast": 32412}, {"timestamp": "2009-07-09 22:40", "programmed": 31963, "forecast": 32182}, {"timestamp": "2009-07-09 22:50", "programmed": 31963, "forecast": 31834}, {"timestamp": "2009-07-09 23:00", "programmed": 29954, "forecast": 31368}, {"timestamp": "2009-07-09 23:10", "programmed": 29954, "forecast": 30862}, {"timestamp": "2009-07-09 23:20", "programmed": 29954, "forecast": 30387}, {"timestamp": "2009-07-09 23:30", "programmed": 29954, "forecast": 29946}, {"timestamp": "2009-07-09 23:40", "programmed": 29954, "forecast": 29537}, {"timestamp": "2009-07-09 23:50", "programmed": 29954, "forecast": 29161}, {"timestamp": "2009-07-10 00:00", "programmed": 27606, "forecast": 28817}, {"timestamp": "2009-07-10 00:10", "programmed": 27606, "forecast": 28485}, {"timestamp": "2009-07-10 00:20", "programmed": 27606, "forecast": 28142}, {"timestamp": "2009-07-10 00:30", "programmed": 27606, "forecast": 27788}, {"timestamp": "2009-07-10 00:40", "programmed": 27606, "forecast": 27424}, {"timestamp": "2009-07-10 00:50", "programmed": 27606, "forecast": 27049}, {"timestamp": "2009-07-10 01:00", "programmed": 25510, "forecast": 26662}, {"timestamp": "2009-07-10 01:10", "programmed": 25510, "forecast": 26286}, {"timestamp": "2009-07-10 01:20", "programmed": 25510, "forecast": 25939}, {"timestamp": "2009-07-10 01:30", "programmed": 25510, "forecast": 25622}, {"timestamp": "2009-07-10 01:40", "programmed": 25510, "forecast": 25335}, {"timestamp": "2009-07-10 01:50", "programmed": 25510, "forecast": 25078}, {"timestamp": "2009-07-10 02:00", "programmed": 24236, "forecast": 24849}, {"timestamp": "2009-07-10 02:10", "programmed": 24236, "forecast": 24647}, {"timestamp": "2009-07-10 02:20", "programmed": 24236, "forecast": 24467}, {"timestamp": "2009-07-10 02:30", "programmed": 24236, "forecast": 24310}, {"timestamp": "2009-07-10 02:40", "programmed": 24236, "forecast": 24174}, {"timestamp": "2009-07-10 02:50", "programmed": 24236, "forecast": 24060}, {"timestamp": "2009-07-10 03:00", "programmed": 23486, "forecast": 23968}, {"timestamp": "2009-07-10 03:10", "programmed": 23486, "forecast": 23891}, {"timestamp": "2009-07-10 03:20", "programmed": 23486, "forecast": 23822}, {"timestamp": "2009-07-10 03:30", "programmed": 23486, "forecast": 23760}, {"timestamp": "2009-07-10 03:40", "programmed": 23486, "forecast": 23706}, {"timestamp": "2009-07-10 03:50", "programmed": 23486, "forecast": 23660}, {"timestamp": "2009-07-10 04:00", "programmed": 23462, "forecast": 23620}, {"timestamp": "2009-07-10 04:10", "programmed": 23462, "forecast": 23587}, {"timestamp": "2009-07-10 04:20", "programmed": 23462, "forecast": 23558}, {"timestamp": "2009-07-10 04:30", "programmed": 23462, "forecast": 23532}, {"timestamp": "2009-07-10 04:40", "programmed": 23462, "forecast": 23510}, {"timestamp": "2009-07-10 04:50", "programmed": 23462, "forecast": 23492}, {"timestamp": "2009-07-10 05:00", "programmed": 23922, "forecast": 23477}, {"timestamp": "2009-07-10 05:10", "programmed": 23922, "forecast": 23493}, {"timestamp": "2009-07-10 05:20", "programmed": 23922, "forecast": 23567}, {"timestamp": "2009-07-10 05:30", "programmed": 23922, "forecast": 23697}, {"timestamp": "2009-07-10 05:40", "programmed": 23922, "forecast": 23885}, {"timestamp": "2009-07-10 05:50", "programmed": 23922, "forecast": 24131}, {"timestamp": "2009-07-10 06:00", "programmed": 25314, "forecast": 24434}, {"timestamp": "2009-07-10 06:10", "programmed": 25314, "forecast": 24763}, {"timestamp": "2009-07-10 06:20", "programmed": 25314, "forecast": 25087}, {"timestamp": "2009-07-10 06:30", "programmed": 25314, "forecast": 25406}, {"timestamp": "2009-07-10 06:40", "programmed": 25314, "forecast": 25719}, {"timestamp": "2009-07-10 06:50", "programmed": 25314, "forecast": 26028}, {"timestamp": "2009-07-10 07:00", "programmed": 27832, "forecast": 26332}, {"timestamp": "2009-07-10 07:10", "programmed": 27832, "forecast": 26655}, {"timestamp": "2009-07-10 07:20", "programmed": 27832, "forecast": 27022}, {"timestamp": "2009-07-10 07:30", "programmed": 27832, "forecast": 27432}, {"timestamp": "2009-07-10 07:40", "programmed": 27832, "forecast": 27885}, {"timestamp": "2009-07-10 07:50", "programmed": 27832, "forecast": 28382}, {"timestamp": "2009-07-10 08:00", "programmed": 30434, "forecast": 28924}, {"timestamp": "2009-07-10 08:10", "programmed": 30434, "forecast": 29477}, {"timestamp": "2009-07-10 08:20", "programmed": 30434, "forecast": 30012}, {"timestamp": "2009-07-10 08:30", "programmed": 30434, "forecast": 30529}, {"timestamp": "2009-07-10 08:40", "programmed": 30434, "forecast": 31028}, {"timestamp": "2009-07-10 08:50", "programmed": 30434, "forecast": 31508}, {"timestamp": "2009-07-10 09:00", "programmed": 33239, "forecast": 31971}, {"timestamp": "2009-07-10 09:10", "programmed": 33239, "forecast": 32411}, {"timestamp": "2009-07-10 09:20", "programmed": 33239, "forecast": 32824}, {"timestamp": "2009-07-10 09:30", "programmed": 33239, "forecast": 33212}, {"timestamp": "2009-07-10 09:40", "programmed": 33239, "forecast": 33572}, {"timestamp": "2009-07-10 09:50", "programmed": 33239, "forecast": 33907}, {"timestamp": "2009-07-10 10:00", "programmed": 35255, "forecast": 34216}, {"timestamp": "2009-07-10 10:10", "programmed": 35255, "forecast": 34492}, {"timestamp": "2009-07-10 10:20", "programmed": 35255, "forecast": 34729}, {"timestamp": "2009-07-10 10:30", "programmed": 35255, "forecast": 34927}, {"timestamp": "2009-07-10 10:40", "programmed": 35255, "forecast": 35087}, {"timestamp": "2009-07-10 10:50", "programmed": 35255, "forecast": 35208}, {"timestamp": "2009-07-10 11:00", "programmed": 35628, "forecast": 35291}, {"timestamp": "2009-07-10 11:10", "programmed": 35628, "forecast": 35358}, {"timestamp": "2009-07-10 11:20", "programmed": 35628, "forecast": 35433}, {"timestamp": "2009-07-10 11:30", "programmed": 35628, "forecast": 35516}, {"timestamp": "2009-07-10 11:40", "programmed": 35628, "forecast": 35606}, {"timestamp": "2009-07-10 11:50", "programmed": 35628, "forecast": 35704}, {"timestamp": "2009-07-10 12:00", "programmed": 35995, "forecast": 35810}, {"timestamp": "2009-07-10 12:10", "programmed": 35995, "forecast": 35912}, {"timestamp": "2009-07-10 12:20", "programmed": 35995, "forecast": 35999}, {"timestamp": "2009-07-10 12:30", "programmed": 35995, "forecast": 36072}, {"timestamp": "2009-07-10 12:40", "programmed": 35995, "forecast": 36131}, {"timestamp": "2009-07-10 12:50", "programmed": 35995, "forecast": 36174}, {"timestamp": "2009-07-10 13:00", "programmed": 35872, "forecast": 36203}, {"timestamp": "2009-07-10 13:10", "programmed": 35872, "forecast": 36196}, {"timestamp": "2009-07-10 13:20", "programmed": 35872, "forecast": 36130}, {"timestamp": "2009-07-10 13:30", "programmed": 35872, "forecast": 36005}, {"timestamp": "2009-07-10 13:40", "programmed": 35872, "forecast": 35823}, {"timestamp": "2009-07-10 13:50", "programmed": 35872, "forecast": 35581}, {"timestamp": "2009-07-10 14:00", "programmed": 34469, "forecast": 35280}, {"timestamp": "2009-07-10 14:10", "programmed": 34469, "forecast": 34962}, {"timestamp": "2009-07-10 14:20", "programmed": 34469, "forecast": 34667}, {"timestamp": "2009-07-10 14:30", "programmed": 34469, "forecast": 34395}, {"timestamp": "2009-07-10 14:40", "programmed": 34469, "forecast": 34146}, {"timestamp": "2009-07-10 14:50", "programmed": 34469, "forecast": 33920}, {"timestamp": "2009-07-10 15:00", "programmed": 33468, "forecast": 33716}, {"timestamp": "2009-07-10 15:10", "programmed": 33468, "forecast": 33537}, {"timestamp": "2009-07-10 15:20", "programmed": 33468, "forecast": 33381}, {"timestamp": "2009-07-10 15:30", "programmed": 33468, "forecast": 33250}, {"timestamp": "2009-07-10 15:40", "programmed": 33468, "forecast": 33142}, {"timestamp": "2009-07-10 15:50", "programmed": 33468, "forecast": 33059}, {"timestamp": "2009-07-10 16:00", "programmed": 33576, "forecast": 32999}, {"timestamp": "2009-07-10 16:10", "programmed": 33576, "forecast": 32967}, {"timestamp": "2009-07-10 16:20", "programmed": 33576, "forecast": 32967}, {"timestamp": "2009-07-10 16:30", "programmed": 33576, "forecast": 32997}, {"timestamp": "2009-07-10 16:40", "programmed": 33576, "forecast": 33058}, {"timestamp": "2009-07-10 16:50", "programmed": 33576, "forecast": 33151}, {"timestamp": "2009-07-10 17:00", "programmed": 33396, "forecast": 33274}, {"timestamp": "2009-07-10 17:10", "programmed": 33396, "forecast": 33385}, {"timestamp": "2009-07-10 17:20", "programmed": 33396, "forecast": 33440}, {"timestamp": "2009-07-10 17:30", "programmed": 33396, "forecast": 33439}, {"timestamp": "2009-07-10 17:40", "programmed": 33396, "forecast": 33383}, {"timestamp": "2009-07-10 17:50", "programmed": 33396, "forecast": 33270}, {"timestamp": "2009-07-10 18:00", "programmed": 32649, "forecast": 33101}, {"timestamp": "2009-07-10 18:10", "programmed": 32649, "forecast": 32911}, {"timestamp": "2009-07-10 18:20", "programmed": 32649, "forecast": 32734}, {"timestamp": "2009-07-10 18:30", "programmed": 32649, "forecast": 32571}, {"timestamp": "2009-07-10 18:40", "programmed": 32649, "forecast": 32421}, {"timestamp": "2009-07-10 18:50", "programmed": 32649, "forecast": 32283}, {"timestamp": "2009-07-10 19:00", "programmed": 32400, "forecast": 32159}, {"timestamp": "2009-07-10 19:10", "programmed": 32400, "forecast": 32056}, {"timestamp": "2009-07-10 19:20", "programmed": 32400, "forecast": 31979}, {"timestamp": "2009-07-10 19:30", "programmed": 32400, "forecast": 31930}, {"timestamp": "2009-07-10 19:40", "programmed": 32400, "forecast": 31908}, {"timestamp": "2009-07-10 19:50", "programmed": 32400, "forecast": 31912}, {"timestamp": "2009-07-10 20:00", "programmed": 31760, "forecast": 31944}, {"timestamp": "2009-07-10 20:10", "programmed": 31760, "forecast": 31976}, {"timestamp": "2009-07-10 20:20", "programmed": 31760, "forecast": 31979}, {"timestamp": "2009-07-10 20:30", "programmed": 31760, "forecast": 31955}, {"timestamp": "2009-07-10 20:40", "programmed": 31760, "forecast": 31902}, {"timestamp": "2009-07-10 20:50", "programmed": 31760, "forecast": 31821}, {"timestamp": "2009-07-10 21:00", "programmed": 31643, "forecast": 31714}, {"timestamp": "2009-07-10 21:10", "programmed": 31643, "forecast": 31616}, {"timestamp": "2009-07-10 21:20", "programmed": 31643, "forecast": 31572}, {"timestamp": "2009-07-10 21:30", "programmed": 31643, "forecast": 31581}, {"timestamp": "2009-07-10 21:40", "programmed": 31643, "forecast": 31644}, {"timestamp": "2009-07-10 21:50", "programmed": 31643, "forecast": 31760}, {"timestamp": "2009-07-10 22:00", "programmed": 31916, "forecast": 31930}, {"timestamp": "2009-07-10 22:10", "programmed": 31916, "forecast": 32070}, {"timestamp": "2009-07-10 22:20", "programmed": 31916, "forecast": 32099}, {"timestamp": "2009-07-10 22:30", "programmed": 31916, "forecast": 32015}, {"timestamp": "2009-07-10 22:40", "programmed": 31916, "forecast": 31819}, {"timestamp": "2009-07-10 22:50", "programmed": 31916, "forecast": 31511}, {"timestamp": "2009-07-10 23:00", "programmed": 29698, "forecast": 31090}, {"timestamp": "2009-07-10 23:10", "programmed": 29698, "forecast": 30638}, {"timestamp": "2009-07-10 23:20", "programmed": 29698, "forecast": 30237}, {"timestamp": "2009-07-10 23:30", "programmed": 29698, "forecast": 29886}, {"timestamp": "2009-07-10 23:40", "programmed": 29698, "forecast": 29586}, {"timestamp": "2009-07-10 23:50", "programmed": 29698, "forecast": 29336}, {"timestamp": "2009-07-11 00:00", "programmed": 28123, "forecast": 29135}, {"timestamp": "2009-07-11 00:10", "programmed": 28123, "forecast": 28941}, {"timestamp": "2009-07-11 00:20", "programmed": 28123, "forecast": 28708}, {"timestamp": "2009-07-11 00:30", "programmed": 28123, "forecast": 28436}, {"timestamp": "2009-07-11 00:40", "programmed": 28123, "forecast": 28125}, {"timestamp": "2009-07-11 00:50", "programmed": 28123, "forecast": 27776}, {"timestamp": "2009-07-11 01:00", "programmed": 26090, "forecast": 27386}, {"timestamp": "2009-07-11 01:10", "programmed": 26090, "forecast": 26990}, {"timestamp": "2009-07-11 01:20", "programmed": 26090, "forecast": 26619}, {"timestamp": "2009-07-11 01:30", "programmed": 26090, "forecast": 26272}, {"timestamp": "2009-07-11 01:40", "programmed": 26090, "forecast": 25950}, {"timestamp": "2009-07-11 01:50", "programmed": 26090, "forecast": 25652}, {"timestamp": "2009-07-11 02:00", "programmed": 24547, "forecast": 25379}, {"timestamp": "2009-07-11 02:10", "programmed": 24547, "forecast": 25127}, {"timestamp": "2009-07-11 02:20", "programmed": 24547, "forecast": 24894}, {"timestamp": "2009-07-11 02:30", "programmed": 24547, "forecast": 24678}, {"timestamp": "2009-07-11 02:40", "programmed": 24547, "forecast": 24480}, {"timestamp": "2009-07-11 02:50", "programmed": 24547, "forecast": 24300}, {"timestamp": "2009-07-11 03:00", "programmed": 23505, "forecast": 24137}, {"timestamp": "2009-07-11 03:10", "programmed": 23505, "forecast": 23989}, {"timestamp": "2009-07-11 03:20", "programmed": 23505, "forecast": 23848}, {"timestamp": "2009-07-11 03:30", "programmed": 23505, "forecast": 23717}, {"timestamp": "2009-07-11 03:40", "programmed": 23505, "forecast": 23594}, {"timestamp": "2009-07-11 03:50", "programmed": 23505, "forecast": 23479}]