[{"timestamp": "2013-06-08 21:00", "programmed": 26519, "forecast": 25416}, {"timestamp": "2013-06-08 21:10", "programmed": 26519, "forecast": 25703}, {"timestamp": "2013-06-08 21:20", "programmed": 26519, "forecast": 25962}, {"timestamp": "2013-06-08 21:30", "programmed": 26519, "forecast": 26193}, {"timestamp": "2013-06-08 21:40", "programmed": 26519, "forecast": 26396}, {"timestamp": "2013-06-08 21:50", "programmed": 26519, "forecast": 26572}, {"timestamp": "2013-06-08 22:00", "programmed": 26873, "forecast": 26719}, {"timestamp": "2013-06-08 22:10", "programmed": 26873, "forecast": 26810}, {"timestamp": "2013-06-08 22:20", "programmed": 26873, "forecast": 26818}, {"timestamp": "2013-06-08 22:30", "programmed": 26873, "forecast": 26741}, {"timestamp": "2013-06-08 22:40", "programmed": 26873, "forecast": 26581}, {"timestamp": "2013-06-08 22:50", "programmed": 26873, "forecast": 26338}, {"timestamp": "2013-06-08 23:00", "programmed": 24763, "forecast": 26009}, {"timestamp": "2013-06-08 23:10", "programmed": 24763, "forecast": 25639}, {"timestamp": "2013-06-08 23:20", "programmed": 24763, "forecast": 25269}, {"timestamp": "2013-06-08 23:30", "programmed": 24763, "forecast": 24899}, {"timestamp": "2013-06-08 23:40", "programmed": 24763, "forecast": 24529}, {"timestamp": "2013-06-08 23:50", "programmed": 24763, "forecast": 24158}, {"timestamp": "2013-06-09 00:00", "programmed": 22889, "forecast": 23787}, {"timestamp": "2013-06-09 00:10", "programmed": 22889, "forecast": 23429}, {"timestamp": "2013-06-09 00:20", "programmed": 22889, "forecast": 23098}, {"timestamp": "2013-06-09 00:30", "programmed": 22889, "forecast": 22793}, {"timestamp": "2013-06-09 00:40", "programmed": 22889, "forecast": 22515}, {"timestamp": "2013-06-09 00:50", "programmed": 22889, "forecast": 22263}, {"timestamp": "2013-06-09 01:00", "programmed": 20993, "forecast": 22037}, {"timestamp": "2013-06-09 01:10", "programmed": 20993, "forecast": 21827}, {"timestamp": "2013-06-09 01:20", "programmed": 20993, "forecast": 21621}, {"timestamp": "2013-06-09 01:30", "programmed": 20993, "forecast": 21419}, {"timestamp": "2013-06-09 01:40", "programmed": 20993, "forecast": 21222}, {"timestamp": "2013-06-09 01:50", "programmed": 20993, "forecast": 21029}, {"timestamp": "2013-06-09 02:00", "programmed": 20046, "forecast": 20839}, {"timestamp": "2013-06-09 02:10", "programmed": 20046, "forecast": 20659}, {"timestamp": "2013-06-09 02:20", "programmed": 20046, "forecast": 20492}, {"timestamp": "2013-06-09 02:30", "programmed": 20046, "forecast": 20337}, {"timestamp": "2013-06-09 02:40", "programmed": 20046, "forecast": 20196}, {"timestamp": "2013-06-09 02:50", "programmed": 20046, "forecast": 20067}, {"timestamp": "2013-06-09 03:00", "programmed": 19301, "forecast": 19952}, {"timestamp": "2013-06-09 03:10", "programmed": 19301, "forecast": 19846}, {"timestamp": "2013-06-09 03:20", "programmed": 19301, "forecast": 19746}, {"timestamp": "2013-06-09 03:30", "programmed": 19301, "forecast": 19653}, {"timestamp": "2013-06-09 03:40", "programmed": 19301, "forecast": 19566}, {"timestamp": "2013-06-09 03:50", "programmed": 19301, "forecast": 19486}, {"timestamp": "2013-06-09 04:00", "programmed": 18811, "forecast": 19411}, {"timestamp": "2013-06-09 04:10", "programmed": 18811, "forecast": 19346}, {"timestamp": "2013-06-09 04:20", "programmed": 18811, "forecast": 19292}, {"timestamp": "2013-06-09 04:30", "programmed": 18811, "forecast": 19249}, {"timestamp": "2013-06-09 04:40", "programmed": 18811, "forecast": 19217}, {"timestamp": "2013-06-09 04:50", "programmed": 18811, "forecast": 19196}, {"timestamp": "2013-06-09 05:00", "programmed": 18989, "forecast": 19187}, {"timestamp": "2013-06-09 05:10", "programmed": 18989, "forecast": 19182}, {"timestamp": "2013-06-09 05:20", "programmed": 18989, "forecast": 19174}, {"timestamp": "2013-06-09 05:30", "programmed": 18989, "forecast": 19164}, {"timestamp": "2013-06-09 05:40", "programmed": 18989, "forecast": 19150}, {"timestamp": "2013-06-09 05:50", "programmed": 18989, "forecast": 19134}, {"timestamp": "2013-06-09 06:00", "programmed": 18924, "forecast": 19115}, {"timestamp": "2013-06-09 06:10", "programmed": 18924, "forecast": 19083}, {"timestamp": "2013-06-09 06:20", "programmed": 18924, "forecast": 19029}, {"timestamp": "2013-06-09 06:30", "programmed": 18924, "forecast": 18953}, {"timestamp": "2013-06-09 06:40", "programmed": 18924, "forecast": 18855}, {"timestamp": "2013-06-09 06:50", "programmed": 18924, "forecast": 18734}, {"timestamp": "2013-06-09 07:00", "programmed": 17881, "forecast": 18591}, {"timestamp": "2013-06-09 07:10", "programmed": 17881, "forecast": 18469}, {"timestamp": "2013-06-09 07:20", "programmed": 17881, "forecast": 18413}, {"timestamp": "2013-06-09 07:30", "programmed": 17881, "forecast": 18422}, {"timestamp": "2013-06-09 07:40", "programmed": 17881, "forecast": 18497}, {"timestamp": "2013-06-09 07:50", "programmed": 17881, "forecast": 18637}, {"timestamp": "2013-06-09 08:00", "programmed": 18864, "forecast": 18843}, {"timestamp": "2013-06-09 08:10", "programmed": 18864, "forecast": 19089}, {"timestamp": "2013-06-09 08:20", "programmed": 18864, "forecast": 19349}, {"timestamp": "2013-06-09 08:30", "programmed": 18864, "forecast": 19624}, {"timestamp": "2013-06-09 08:40", "programmed": 18864, "forecast": 19914}, {"timestamp": "2013-06-09 08:50", "programmed": 18864, "forecast": 20218}, {"timestamp": "2013-06-09 09:00", "programmed": 21289, "forecast": 20538}, {"timestamp": "2013-06-09 09:10", "programmed": 21289, "forecast": 20864}, {"timestamp": "2013-06-09 09:20", "programmed": 21289, "forecast": 21189}, {"timestamp": "2013-06-09 09:30", "programmed": 21289, "forecast": 21513}, {"timestamp": "2013-06-09 09:40", "programmed": 21289, "forecast": 21835}, {"timestamp": "2013-06-09 09:50", "programmed": 21289, "forecast": 22157}, {"timestamp": "2013-06-09 10:00", "programmed": 23401, "forecast": 22478}, {"timestamp": "2013-06-09 10:10", "programmed": 23401, "forecast": 22789}, {"timestamp": "2013-06-09 10:20", "programmed": 23401, "forecast": 23082}, {"timestamp": "2013-06-09 10:30", "programmed": 23401, "forecast": 23356}, {"timestamp": "2013-06-09 10:40", "programmed": 23401, "forecast": 23613}, {"timestamp": "2013-06-09 10:50", "programmed": 23401, "forecast": 23851}, {"timestamp": "2013-06-09 11:00", "programmed": 24544, "forecast": 24072}, {"timestamp": "2013-06-09 11:10", "programmed": 24544, "forecast": 24266}, {"timestamp": "2013-06-09 11:20", "programmed": 24544, "forecast": 24422}, {"timestamp": "2013-06-09 11:30", "programmed": 24544, "forecast": 24543}, {"timestamp": "2013-06-09 11:40", "programmed": 24544, "forecast": 24627}, {"timestamp": "2013-06-09 11:50", "programmed": 24544, "forecast": 24675}, {"timestamp": "2013-06-09 12:00", "programmed": 24767, "forecast": 24686}, {"timestamp": "2013-06-09 12:10", "programmed": 24767, "forecast": 24690}, {"timestamp": "2013-06-09 12:20", "programmed": 24767, "forecast": 24715}, {"timestamp": "2013-06-09 12:30", "programmed": 24767, "forecast": 24760}, {"timestamp": "2013-06-09 12:40", "programmed": 24767, "forecast": 24826}, {"timestamp": "2013-06-09 12:50", "programmed": 24767, "forecast": 24914}, {"timestamp": "2013-06-09 13:00", "programmed": 25197, "forecast": 25022}, {"timestamp": "2013-06-09 13:10", "programmed": 25197, "forecast": 25129}, {"timestamp": "2013-06-09 13:20", "programmed": 25197, "forecast": 25215}, {"timestamp": "2013-06-09 13:30", "programmed": 25197, "forecast": 25279}, {"timestamp": "2013-06-09 13:40", "programmed": 25197, "forecast": 25321}, {"timestamp": "2013-06-09 13:50", "programmed": 25197, "forecast": 25342}, {"timestamp": "2013-06-09 14:00", "programmed": 25385, "forecast": 25340}, {"timestamp": "2013-06-09 14:10", "programmed": 25385, "forecast": 25308}, {"timestamp": "2013-06-09 14:20", "programmed": 25385, "forecast": 25238}, {"timestamp": "2013-06-09 14:30", "programmed": 25385, "forecast": 25129}, {"timestamp": "2013-06-09 14:40", "programmed": 25385, "forecast": 24981}, {"timestamp": "2013-06-09 14:50", "programmed": 25385, "forecast": 24795}, {"timestamp": "2013-06-09 15:00", "programmed": 23857, "forecast": 24569}, {"timestamp": "2013-06-09 15:10", "programmed": 23857, "forecast": 24334}, {"timestamp": "2013-06-09 15:20", "programmed": 23857, "forecast": 24116}, {"timestamp": "2013-06-09 15:30", "programmed": 23857, "forecast": 23917}, {"timestamp": "2013-06-09 15:40", "programmed": 23857, "forecast": 23735}, {"timestamp": "2013-06-09 15:50", "programmed": 23857, "forecast": 23572}, {"timestamp": "2013-06-09 16:00", "programmed": 22808, "forecast": 23426}, {"timestamp": "2013-06-09 16:10", "programmed": 22808, "forecast": 23296}, {"timestamp": "2013-06-09 16:20", "programmed": 22808, "forecast": 23179}, {"timestamp": "2013-06-09 16:30", "programmed": 22808, "forecast": 23076}, {"timestamp": "2013-06-09 16:40", "programmed": 22808, "forecast": 22987}, {"timestamp": "2013-06-09 16:50", "programmed": 22808, "forecast": 22911}, {"timestamp": "2013-06-09 17:00", "programmed": 22604, "forecast": 22848}, {"timestamp": "2013-06-09 17:10", "programmed": 22604, "forecast": 22793}, {"timestamp": "2013-06-09 17:20", "programmed": 22604, "forecast": 22741}, {"timestamp": "2013-06-09 17:30", "programmed": 22604, "forecast": 22692}, {"timestamp": "2013-06-09 17:40", "programmed": 22604, "forecast": 22646}, {"timestamp": "2013-06-09 17:50", "programmed": 22604, "forecast": 22603}, {"timestamp": "2013-06-09 18:00", "programmed": 22544, "forecast": 22562}, {"timestamp": "2013-06-09 18:10", "programmed": 22544, "forecast": 22537}, {"timestamp": "2013-06-09 18:20", "programmed": 22544, "forecast": 22540}, {"timestamp": "2013-06-09 18:30", "programmed": 22544, "forecast": 22572}, {"timestamp": "2013-06-09 18:40", "programmed": 22544, "forecast": 22632}, {"timestamp": "2013-06-09 18:50", "programmed": 22544, "forecast": 22720}, {"timestamp": "2013-06-09 19:00", "programmed": 23016, "forecast": 22838}, {"timestamp": "2013-06-09 19:10", "programmed": 23016, "forecast": 22966}, {"timestamp": "2013-06-09 19:20", "programmed": 23016, "forecast": 23088}, {"timestamp": "2013-06-09 19:30", "programmed": 23016, "forecast": 23204}, {"timestamp": "2013-06-09 19:40", "programmed": 23016, "forecast": 23313}, {"timestamp": "2013-06-09 19:50", "programmed": 23016, "forecast": 23417}, {"timestamp": "2013-06-09 20:00", "programmed": 24237, "forecast": 23514}, {"timestamp": "2013-06-09 20:10", "programmed": 24237, "forecast": 23626}, {"timestamp": "2013-06-09 20:20", "programmed": 24237, "forecast": 23773}, {"timestamp": "2013-06-09 20:30", "programmed": 24237, "forecast": 23955}, {"timestamp": "2013-06-09 20:40", "programmed": 24237, "forecast": 24173}, {"timestamp": "2013-06-09 20:50", "programmed": 24237, "forecast": 24425}, {"timestamp": "2013-06-09 21:00", "programmed": 25965, "forecast": 24712}, {"timestamp": "2013-06-09 21:10", "programmed": 25965, "forecast": 25023}, {"timestamp": "2013-06-09 21:20", "programmed": 25965, "forecast": 25343}, {"timestamp": "2013-06-09 21:30", "programmed": 25965, "forecast": 25671}, {"timestamp": "2013-06-09 21:40", "programmed": 25965, "forecast": 26008}, {"timestamp": "2013-06-09 21:50", "programmed": 25965, "forecast": 26354}, {"timestamp": "2013-06-09 22:00", "programmed": 26748, "forecast": 26710}, {"timestamp": "2013-06-09 22:10", "programmed": 26748, "forecast": 26990}, {"timestamp": "2013-06-09 22:20", "programmed": 26748, "forecast": 27112}, {"timestamp": "2013-06-09 22:30", "programmed": 26748, "forecast": 27075}, {"timestamp": "2013-06-09 22:40", "programmed": 26748, "forecast": 26881}, {"timestamp": "2013-06-09 22:50", "programmed": 26748, "forecast": 26528}, {"timestamp": "2013-06-09 23:00", "programmed": 25160, "forecast": 26015}, {"timestamp": "2013-06-09 23:10", "programmed": 25160, "forecast": 25452}, {"timestamp": "2013-06-09 23:20", "programmed": 25160, "forecast": 24944}, {"timestamp": "2013-06-09 23:30", "programmed": 25160, "forecast": 24490}, {"timestamp": "2013-06-09 23:40", "programmed": 25160, "forecast": 24091}, {"timestamp": "2013-06-09 23:50", "programmed": 25160, "forecast": 23746}, {"timestamp": "2013-06-10 00:00", "programmed": 22143, "forecast": 23456}, {"timestamp": "2013-06-10 00:10", "programmed": 22143, "forecast": 23192}, {"timestamp": "2013-06-10 00:20", "programmed": 22143, "forecast": 22925}, {"timestamp": "2013-06-10 00:30", "programmed": 22143, "forecast": 22654}, {"timestamp": "2013-06-10 00:40", "programmed": 22143, "forecast": 22380}, {"timestamp": "2013-06-10 00:50", "programmed": 22143, "forecast": 22102}, {"timestamp": "2013-06-10 01:00", "programmed": 20701, "forecast": 21821}, {"timestamp": "2013-06-10 01:10", "programmed": 20701, "forecast": 21549}, {"timestamp": "2013-06-10 01:20", "programmed": 20701, "forecast": 21299}, {"timestamp": "2013-06-10 01:30", "programmed": 20701, "forecast": 21070}, {"timestamp": "2013-06-10 01:40", "programmed": 20701, "forecast": 20863}, {"timestamp": "2013-06-10 01:50", "programmed": 20701, "forecast": 20678}, {"timestamp": "2013-06-10 02:00", "programmed": 19851, "forecast": 20513}, {"timestamp": "2013-06-10 02:10", "programmed": 19851, "forecast": 20367}, {"timestamp": "2013-06-10 02:20", "programmed": 19851, "forecast": 20237}, {"timestamp": "2013-06-10 02:30", "programmed": 19851, "forecast": 20122}, {"timestamp": "2013-06-10 02:40", "programmed": 19851, "forecast": 20023}, {"timestamp": "2013-06-10 02:50", "programmed": 19851, "forecast": 19939}, {"timestamp": "2013-06-10 03:00", "programmed": 19708, "forecast": 19871}, {"timestamp": "2013-06-10 03:10", "programmed": 19708, "forecast": 19816}, {"timestamp": "2013-06-10 03:20", "programmed": 19708, "forecast": 19775}, {"timestamp": "2013-06-10 03:30", "programmed": 19708, "forecast": 19747}, {"timestamp": "2013-06-10 03:40", "programmed": 19708, "forecast": 19732}, {"timestamp": "2013-06-10 03:50", "programmed": 19708, "forecast": 19730}]