[{"timestamp": "2008-06-28 21:00", "programmed": 31392, "forecast": 30955}, {"timestamp": "2008-06-28 21:10", "programmed": 31392, "forecast": 30904}, {"timestamp": "2008-06-28 21:20", "programmed": 31392, "forecast": 30936}, {"timestamp": "2008-06-28 21:30", "programmed": 31392, "forecast": 31051}, {"timestamp": "2008-06-28 21:40", "programmed": 31392, "forecast": 31247}, {"timestamp": "2008-06-28 21:50", "programmed": 31392, "forecast": 31527}, {"timestamp": "2008-06-28 22:00", "programmed": 32567, "forecast": 31889}, {"timestamp": "2008-06-28 22:10", "programmed": 32567, "forecast": 32231}, {"timestamp": "2008-06-28 22:20", "programmed": 32567, "forecast": 32452}, {"timestamp": "2008-06-28 22:30", "programmed": 32567, "forecast": 32550}, {"timestamp": "2008-06-28 22:40", "programmed": 32567, "forecast": 32526}, {"timestamp": "2008-06-28 22:50", "programmed": 32567, "forecast": 32380}, {"timestamp": "2008-06-28 23:00", "programmed": 30777, "forecast": 32111}, {"timestamp": "2008-06-28 23:10", "programmed": 30777, "forecast": 31773}, {"timestamp": "2008-06-28 23:20", "programmed": 30777, "forecast": 31417}, {"timestamp": "2008-06-28 23:30", "programmed": 30777, "forecast": 31043}, {"timestamp": "2008-06-28 23:40", "programmed": 30777, "forecast": 30652}, {"timestamp": "2008-06-28 23:50", "programmed": 30777, "forecast": 30244}, {"timestamp": "2008-06-29 00:00", "programmed": 28576, "forecast": 29816}, {"timestamp": "2008-06-29 00:10", "programmed": 28576, "forecast": 29390}, {"timestamp": "2008-06-29 00:20", "programmed": 28576, "forecast": 28981}, {"timestamp": "2008-06-29 00:30", "programmed": 28576, "forecast": 28589}, {"timestamp": "2008-06-29 00:40", "programmed": 28576, "forecast": 28215}, {"timestamp": "2008-06-29 00:50", "programmed": 28576, "forecast": 27858}, {"timestamp": "2008-06-29 01:00", "programmed": 26236, "forecast": 27517}, {"timestamp": "2008-06-29 01:10", "programmed": 26236, "forecast": 27181}, {"timestamp": "2008-06-29 01:20", "programmed": 26236, "forecast": 26832}, {"timestamp": "2008-06-29 01:30", "programmed": 26236, "forecast": 26472}, {"timestamp": "2008-06-29 01:40", "programmed": 26236, "forecast": 26100}, {"timestamp": "2008-06-29 01:50", "programmed": 26236, "forecast": 25716}, {"timestamp": "2008-06-29 02:00", "programmed": 24765, "forecast": 25319}, {"timestamp": "2008-06-29 02:10", "programmed": 24765, "forecast": 24950}, {"timestamp": "2008-06-29 02:20", "programmed": 24765, "forecast": 24646}, {"timestamp": "2008-06-29 02:30", "programmed": 24765, "forecast": 24408}, {"timestamp": "2008-06-29 02:40", "programmed": 24765, "forecast": 24235}, {"timestamp": "2008-06-29 02:50", "programmed": 24765, "forecast": 24127}, {"timestamp": "2008-06-29 03:00", "programmed": 23672, "forecast": 24084}, {"timestamp": "2008-06-29 03:10", "programmed": 23672, "forecast": 24062}, {"timestamp": "2008-06-29 03:20", "programmed": 23672, "forecast": 24015}, {"timestamp": "2008-06-29 03:30", "programmed": 23672, "forecast": 23943}, {"timestamp": "2008-06-29 03:40", "programmed": 23672, "forecast": 23846}, {"timestamp": "2008-06-29 03:50", "programmed": 23672, "forecast": 23724}, {"timestamp": "2008-06-29 04:00", "programmed": 22986, "forecast": 23576}, {"timestamp": "2008-06-29 04:10", "programmed": 22986, "forecast": 23425}, {"timestamp": "2008-06-29 04:20", "programmed": 22986, "forecast": 23292}, {"timestamp": "2008-06-29 04:30", "programmed": 22986, "forecast": 23175}, {"timestamp": "2008-06-29 04:40", "programmed": 22986, "forecast": 23077}, {"timestamp": "2008-06-29 04:50", "programmed": 22986, "forecast": 22995}, {"timestamp": "2008-06-29 05:00", "programmed": 22622, "forecast": 22931}, {"timestamp": "2008-06-29 05:10", "programmed": 22622, "forecast": 22874}, {"timestamp": "2008-06-29 05:20", "programmed": 22622, "forecast": 22814}, {"timestamp": "2008-06-29 05:30", "programmed": 22622, "forecast": 22749}, {"timestamp": "2008-06-29 05:40", "programmed": 22622, "forecast": 22681}, {"timestamp": "2008-06-29 05:50", "programmed": 22622, "forecast": 22609}, {"timestamp": "2008-06-29 06:00", "programmed": 21954, "forecast": 22533}, {"timestamp": "2008-06-29 06:10", "programmed": 21954, "forecast": 22442}, {"timestamp": "2008-06-29 06:20", "programmed": 21954, "forecast": 22323}, {"timestamp": "2008-06-29 06:30", "programmed": 21954, "forecast": 22177}, {"timestamp": "2008-06-29 06:40", "programmed": 21954, "forecast": 22003}, {"timestamp": "2008-06-29 06:50", "programmed": 21954, "forecast": 21802}, {"timestamp": "2008-06-29 07:00", "programmed": 21125, "forecast": 21572}, {"timestamp": "2008-06-29 07:10", "programmed": 21125, "forecast": 21368}, {"timestamp": "2008-06-29 07:20", "programmed": 21125, "forecast": 21239}, {"timestamp": "2008-06-29 07:30", "programmed": 21125, "forecast": 21186}, {"timestamp": "2008-06-29 07:40", "programmed": 21125, "forecast": 21208}, {"timestamp": "2008-06-29 07:50", "programmed": 21125, "forecast": 21307}, {"timestamp": "2008-06-29 08:00", "programmed": 22560, "forecast": 21482}, {"timestamp": "2008-06-29 08:10", "programmed": 22560, "forecast": 21698}, {"timestamp": "2008-06-29 08:20", "programmed": 22560, "forecast": 21920}, {"timestamp": "2008-06-29 08:30", "programmed": 22560, "forecast": 22149}, {"timestamp": "2008-06-29 08:40", "programmed": 22560, "forecast": 22384}, {"timestamp": "2008-06-29 08:50", "programmed": 22560, "forecast": 22625}, {"timestamp": "2008-06-29 09:00", "programmed": 24031, "forecast": 22874}, {"timestamp": "2008-06-29 09:10", "programmed": 24031, "forecast": 23139}, {"timestamp": "2008-06-29 09:20", "programmed": 24031, "forecast": 23432}, {"timestamp": "2008-06-29 09:30", "programmed": 24031, "forecast": 23753}, {"timestamp": "2008-06-29 09:40", "programmed": 24031, "forecast": 24102}, {"timestamp": "2008-06-29 09:50", "programmed": 24031, "forecast": 24479}, {"timestamp": "2008-06-29 10:00", "programmed": 25809, "forecast": 24884}, {"timestamp": "2008-06-29 10:10", "programmed": 25809, "forecast": 25290}, {"timestamp": "2008-06-29 10:20", "programmed": 25809, "forecast": 25669}, {"timestamp": "2008-06-29 10:30", "programmed": 25809, "forecast": 26023}, {"timestamp": "2008-06-29 10:40", "programmed": 25809, "forecast": 26351}, {"timestamp": "2008-06-29 10:50", "programmed": 25809, "forecast": 26653}, {"timestamp": "2008-06-29 11:00", "programmed": 27241, "forecast": 26929}, {"timestamp": "2008-06-29 11:10", "programmed": 27241, "forecast": 27178}, {"timestamp": "2008-06-29 11:20", "programmed": 27241, "forecast": 27402}, {"timestamp": "2008-06-29 11:30", "programmed": 27241, "forecast": 27598}, {"timestamp": "2008-06-29 11:40", "programmed": 27241, "forecast": 27768}, {"timestamp": "2008-06-29 11:50", "programmed": 27241, "forecast": 27912}, {"timestamp": "2008-06-29 12:00", "programmed": 28204, "forecast": 28029}, {"timestamp": "2008-06-29 12:10", "programmed": 28204, "forecast": 28138}, {"timestamp": "2008-06-29 12:20", "programmed": 28204, "forecast": 28256}, {"timestamp": "2008-06-29 12:30", "programmed": 28204, "forecast": 28385}, {"timestamp": "2008-06-29 12:40", "programmed": 28204, "forecast": 28524}, {"timestamp": "2008-06-29 12:50", "programmed": 28204, "forecast": 28673}, {"timestamp": "2008-06-29 13:00", "programmed": 29217, "forecast": 28832}, {"timestamp": "2008-06-29 13:10", "programmed": 29217, "forecast": 28992}, {"timestamp": "2008-06-29 13:20", "programmed": 29217, "forecast": 29142}, {"timestamp": "2008-06-29 13:30", "programmed": 29217, "forecast": 29282}, {"timestamp": "2008-06-29 13:40", "programmed": 29217, "forecast": 29414}, {"timestamp": "2008-06-29 13:50", "programmed": 29217, "forecast": 29536}, {"timestamp": "2008-06-29 14:00", "programmed": 29190, "forecast": 29649}, {"timestamp": "2008-06-29 14:10", "programmed": 29190, "forecast": 29723}, {"timestamp": "2008-06-29 14:20", "programmed": 29190, "forecast": 29731}, {"timestamp": "2008-06-29 14:30", "programmed": 29190, "forecast": 29672}, {"timestamp": "2008-06-29 14:40", "programmed": 29190, "forecast": 29546}, {"timestamp": "2008-06-29 14:50", "programmed": 29190, "forecast": 29353}, {"timestamp": "2008-06-29 15:00", "programmed": 28945, "forecast": 29093}, {"timestamp": "2008-06-29 15:10", "programmed": 28945, "forecast": 28829}, {"timestamp": "2008-06-29 15:20", "programmed": 28945, "forecast": 28623}, {"timestamp": "2008-06-29 15:30", "programmed": 28945, "forecast": 28476}, {"timestamp": "2008-06-29 15:40", "programmed": 28945, "forecast": 28386}, {"timestamp": "2008-06-29 15:50", "programmed": 28945, "forecast": 28354}, {"timestamp": "2008-06-29 16:00", "programmed": 28078, "forecast": 28380}, {"timestamp": "2008-06-29 16:10", "programmed": 28078, "forecast": 28422}, {"timestamp": "2008-06-29 16:20", "programmed": 28078, "forecast": 28439}, {"timestamp": "2008-06-29 16:30", "programmed": 28078, "forecast": 28431}, {"timestamp": "2008-06-29 16:40", "programmed": 28078, "forecast": 28397}, {"timestamp": "2008-06-29 16:50", "programmed": 28078, "forecast": 28337}, {"timestamp": "2008-06-29 17:00", "programmed": 28619, "forecast": 28252}, {"timestamp": "2008-06-29 17:10", "programmed": 28619, "forecast": 28169}, {"timestamp": "2008-06-29 17:20", "programmed": 28619, "forecast": 28117}, {"timestamp": "2008-06-29 17:30", "programmed": 28619, "forecast": 28095}, {"timestamp": "2008-06-29 17:40", "programmed": 28619, "forecast": 28103}, {"timestamp": "2008-06-29 17:50", "programmed": 28619, "forecast": 28142}, {"timestamp": "2008-06-29 18:00", "programmed": 28919, "forecast": 28212}, {"timestamp": "2008-06-29 18:10", "programmed": 28919, "forecast": 28295}, {"timestamp": "2008-06-29 18:20", "programmed": 28919, "forecast": 28376}, {"timestamp": "2008-06-29 18:30", "programmed": 28919, "forecast": 28455}, {"timestamp": "2008-06-29 18:40", "programmed": 28919, "forecast": 28531}, {"timestamp": "2008-06-29 18:50", "programmed": 28919, "forecast": 28605}, {"timestamp": "2008-06-29 19:00", "programmed": 29319, "forecast": 28677}, {"timestamp": "2008-06-29 19:10", "programmed": 29319, "forecast": 28758}, {"timestamp": "2008-06-29 19:20", "programmed": 29319, "forecast": 28858}, {"timestamp": "2008-06-29 19:30", "programmed": 29319, "forecast": 28979}, {"timestamp": "2008-06-29 19:40", "programmed": 29319, "forecast": 29120}, {"timestamp": "2008-06-29 19:50", "programmed": 29319, "forecast": 29281}, {"timestamp": "2008-06-29 20:00", "programmed": 30230, "forecast": 29463}, {"timestamp": "2008-06-29 20:10", "programmed": 30230, "forecast": 29637}, {"timestamp": "2008-06-29 20:20", "programmed": 30230, "forecast": 29778}, {"timestamp": "2008-06-29 20:30", "programmed": 30230, "forecast": 29884}, {"timestamp": "2008-06-29 20:40", "programmed": 30230, "forecast": 29956}, {"timestamp": "2008-06-29 20:50", "programmed": 30230, "forecast": 29993}, {"timestamp": "2008-06-29 21:00", "programmed": 31351, "forecast": 29995}, {"timestamp": "2008-06-29 21:10", "programmed": 31351, "forecast": 30027}, {"timestamp": "2008-06-29 21:20", "programmed": 31351, "forecast": 30148}, {"timestamp": "2008-06-29 21:30", "programmed": 31351, "forecast": 30359}, {"timestamp": "2008-06-29 21:40", "programmed": 31351, "forecast": 30659}, {"timestamp": "2008-06-29 21:50", "programmed": 31351, "forecast": 31048}, {"timestamp": "2008-06-29 22:00", "programmed": 32310, "forecast": 31528}, {"timestamp": "2008-06-29 22:10", "programmed": 32310, "forecast": 31985}, {"timestamp": "2008-06-29 22:20", "programmed": 32310, "forecast": 32309}, {"timestamp": "2008-06-29 22:30", "programmed": 32310, "forecast": 32499}, {"timestamp": "2008-06-29 22:40", "programmed": 32310, "forecast": 32555}, {"timestamp": "2008-06-29 22:50", "programmed": 32310, "forecast": 32479}, {"timestamp": "2008-06-29 23:00", "programmed": 30893, "forecast": 32268}, {"timestamp": "2008-06-29 23:10", "programmed": 30893, "forecast": 31964}, {"timestamp": "2008-06-29 23:20", "programmed": 30893, "forecast": 31607}, {"timestamp": "2008-06-29 23:30", "programmed": 30893, "forecast": 31196}, {"timestamp": "2008-06-29 23:40", "programmed": 30893, "forecast": 30732}, {"timestamp": "2008-06-29 23:50", "programmed": 30893, "forecast": 30215}, {"timestamp": "2008-06-30 00:00", "programmed": 28493, "forecast": 29643}, {"timestamp": "2008-06-30 00:10", "programmed": 28493, "forecast": 29064}, {"timestamp": "2008-06-30 00:20", "programmed": 28493, "forecast": 28521}, {"timestamp": "2008-06-30 00:30", "programmed": 28493, "forecast": 28014}, {"timestamp": "2008-06-30 00:40", "programmed": 28493, "forecast": 27543}, {"timestamp": "2008-06-30 00:50", "programmed": 28493, "forecast": 27109}, {"timestamp": "2008-06-30 01:00", "programmed": 25702, "forecast": 26710}, {"timestamp": "2008-06-30 01:10", "programmed": 25702, "forecast": 26344}, {"timestamp": "2008-06-30 01:20", "programmed": 25702, "forecast": 26008}, {"timestamp": "2008-06-30 01:30", "programmed": 25702, "forecast": 25701}, {"timestamp": "2008-06-30 01:40", "programmed": 25702, "forecast": 25423}, {"timestamp": "2008-06-30 01:50", "programmed": 25702, "forecast": 25174}, {"timestamp": "2008-06-30 02:00", "programmed": 24496, "forecast": 24954}, {"timestamp": "2008-06-30 02:10", "programmed": 24496, "forecast": 24758}, {"timestamp": "2008-06-30 02:20", "programmed": 24496, "forecast": 24579}, {"timestamp": "2008-06-30 02:30", "programmed": 24496, "forecast": 24417}, {"timestamp": "2008-06-30 02:40", "programmed": 24496, "forecast": 24272}, {"timestamp": "2008-06-30 02:50", "programmed": 24496, "forecast": 24145}, {"timestamp": "2008-06-30 03:00", "programmed": 23767, "forecast": 24034}, {"timestamp": "2008-06-30 03:10", "programmed": 23767, "forecast": 23938}, {"timestamp": "2008-06-30 03:20", "programmed": 23767, "forecast": 23852}, {"timestamp": "2008-06-30 03:30", "programmed": 23767, "forecast": 23777}, {"timestamp": "2008-06-30 03:40", "programmed": 23767, "forecast": 23713}, {"timestamp": "2008-06-30 03:50", "programmed": 23767, "forecast": 23660}]