[{"timestamp": "2009-07-12 21:00", "programmed": 28621, "forecast": 27151}, {"timestamp": "2009-07-12 21:10", "programmed": 28621, "forecast": 27454}, {"timestamp": "2009-07-12 21:20", "programmed": 28621, "forecast": 27793}, {"timestamp": "2009-07-12 21:30", "programmed": 28621, "forecast": 28170}, {"timestamp": "2009-07-12 21:40", "programmed": 28621, "forecast": 28583}, {"timestamp": "2009-07-12 21:50", "programmed": 28621, "forecast": 29033}, {"timestamp": "2009-07-12 22:00", "programmed": 30350, "forecast": 29521}, {"timestamp": "2009-07-12 22:10", "programmed": 30350, "forecast": 29950}, {"timestamp": "2009-07-12 22:20", "programmed": 30350, "forecast": 30224}, {"timestamp": "2009-07-12 22:30", "programmed": 30350, "forecast": 30345}, {"timestamp": "2009-07-12 22:40", "programmed": 30350, "forecast": 30312}, {"timestamp": "2009-07-12 22:50", "programmed": 30350, "forecast": 30126}, {"timestamp": "2009-07-12 23:00", "programmed": 28854, "forecast": 29784}, {"timestamp": "2009-07-12 23:10", "programmed": 28854, "forecast": 29369}, {"timestamp": "2009-07-12 23:20", "programmed": 28854, "forecast": 28959}, {"timestamp": "2009-07-12 23:30", "programmed": 28854, "forecast": 28555}, {"timestamp": "2009-07-12 23:40", "programmed": 28854, "forecast": 28156}, {"timestamp": "2009-07-12 23:50", "programmed": 28854, "forecast": 27762}, {"timestamp": "2009-07-13 00:00", "programmed": 26331, "forecast": 27373}, {"timestamp": "2009-07-13 00:10", "programmed": 26331, "forecast": 26989}, {"timestamp": "2009-07-13 00:20", "programmed": 26331, "forecast": 26607}, {"timestamp": "2009-07-13 00:30", "programmed": 26331, "forecast": 26229}, {"timestamp": "2009-07-13 00:40", "programmed": 26331, "forecast": 25853}, {"timestamp": "2009-07-13 00:50", "programmed": 26331, "forecast": 25480}, {"timestamp": "2009-07-13 01:00", "programmed": 24484, "forecast": 25109}, {"timestamp": "2009-07-13 01:10", "programmed": 24484, "forecast": 24751}, {"timestamp": "2009-07-13 01:20", "programmed": 24484, "forecast": 24417}, {"timestamp": "2009-07-13 01:30", "programmed": 24484, "forecast": 24105}, {"timestamp": "2009-07-13 01:40", "programmed": 24484, "forecast": 23815}, {"timestamp": "2009-07-13 01:50", "programmed": 24484, "forecast": 23549}, {"timestamp": "2009-07-13 02:00", "programmed": 22768, "forecast": 23305}, {"timestamp": "2009-07-13 02:10", "programmed": 22768, "forecast": 23083}, {"timestamp": "2009-07-13 02:20", "programmed": 22768, "forecast": 22885}, {"timestamp": "2009-07-13 02:30", "programmed": 22768, "forecast": 22708}, {"timestamp": "2009-07-13 02:40", "programmed": 22768, "forecast": 22554}, {"timestamp": "2009-07-13 02:50", "programmed": 22768, "forecast": 22422}, {"timestamp": "2009-07-13 03:00", "programmed": 22077, "forecast": 22313}, {"timestamp": "2009-07-13 03:10", "programmed": 22077, "forecast": 22222}, {"timestamp": "2009-07-13 03:20", "programmed": 22077, "forecast": 22147}, {"timestamp": "2009-07-13 03:30", "programmed": 22077, "forecast": 22088}, {"timestamp": "2009-07-13 03:40", "programmed": 22077, "forecast": 22045}, {"timestamp": "2009-07-13 03:50", "programmed": 22077, "forecast": 22016}, {"timestamp": "2009-07-13 04:00", "programmed": 21926, "forecast": 22004}, {"timestamp": "2009-07-13 04:10", "programmed": 21926, "forecast": 22001}, {"timestamp": "2009-07-13 04:20", "programmed": 21926, "forecast": 22001}, {"timestamp": "2009-07-13 04:30", "programmed": 21926, "forecast": 22005}, {"timestamp": "2009-07-13 04:40", "programmed": 21926, "forecast": 22013}, {"timestamp": "2009-07-13 04:50", "programmed": 21926, "forecast": 22023}, {"timestamp": "2009-07-13 05:00", "programmed": 22293, "forecast": 22038}, {"timestamp": "2009-07-13 05:10", "programmed": 22293, "forecast": 22093}, {"timestamp": "2009-07-13 05:20", "programmed": 22293, "forecast": 22229}, {"timestamp": "2009-07-13 05:30", "programmed": 22293, "forecast": 22445}, {"timestamp": "2009-07-13 05:40", "programmed": 22293, "forecast": 22741}, {"timestamp": "2009-07-13 05:50", "programmed": 22293, "forecast": 23117}, {"timestamp": "2009-07-13 06:00", "programmed": 24298, "forecast": 23574}, {"timestamp": "2009-07-13 06:10", "programmed": 24298, "forecast": 24058}, {"timestamp": "2009-07-13 06:20", "programmed": 24298, "forecast": 24518}, {"timestamp": "2009-07-13 06:30", "programmed": 24298, "forecast": 24954}, {"timestamp": "2009-07-13 06:40", "programmed": 24298, "forecast": 25366}, {"timestamp": "2009-07-13 06:50", "programmed": 24298, "forecast": 25755}, {"timestamp": "2009-07-13 07:00", "programmed": 27335, "forecast": 26120}, {"timestamp": "2009-07-13 07:10", "programmed": 27335, "forecast": 26498}, {"timestamp": "2009-07-13 07:20", "programmed": 27335, "forecast": 26926}, {"timestamp": "2009-07-13 07:30", "programmed": 27335, "forecast": 27405}, {"timestamp": "2009-07-13 07:40", "programmed": 27335, "forecast": 27934}, {"timestamp": "2009-07-13 07:50", "programmed": 27335, "forecast": 28514}, {"timestamp": "2009-07-13 08:00", "programmed": 30544, "forecast": 29146}, {"timestamp": "2009-07-13 08:10", "programmed": 30544, "forecast": 29785}, {"timestamp": "2009-07-13 08:20", "programmed": 30544, "forecast": 30390}, {"timestamp": "2009-07-13 08:30", "programmed": 30544, "forecast": 30961}, {"timestamp": "2009-07-13 08:40", "programmed": 30544, "forecast": 31499}, {"timestamp": "2009-07-13 08:50", "programmed": 30544, "forecast": 32003}, {"timestamp": "2009-07-13 09:00", "programmed": 33363, "forecast": 32475}, {"timestamp": "2009-07-13 09:10", "programmed": 33363, "forecast": 32927}, {"timestamp": "2009-07-13 09:20", "programmed": 33363, "forecast": 33377}, {"timestamp": "2009-07-13 09:30", "programmed": 33363, "forecast": 33823}, {"timestamp": "2009-07-13 09:40", "programmed": 33363, "forecast": 34266}, {"timestamp": "2009-07-13 09:50", "programmed": 33363, "forecast": 34705}, {"timestamp": "2009-07-13 10:00", "programmed": 36566, "forecast": 35143}, {"timestamp": "2009-07-13 10:10", "programmed": 36566, "forecast": 35559}, {"timestamp": "2009-07-13 10:20", "programmed": 36566, "forecast": 35937}, {"timestamp": "2009-07-13 10:30", "programmed": 36566, "forecast": 36277}, {"timestamp": "2009-07-13 10:40", "programmed": 36566, "forecast": 36579}, {"timestamp": "2009-07-13 10:50", "programmed": 36566, "forecast": 36843}, {"timestamp": "2009-07-13 11:00", "programmed": 37829, "forecast": 37069}, {"timestamp": "2009-07-13 11:10", "programmed": 37829, "forecast": 37277}, {"timestamp": "2009-07-13 11:20", "programmed": 37829, "forecast": 37486}, {"timestamp": "2009-07-13 11:30", "programmed": 37829, "forecast": 37697}, {"timestamp": "2009-07-13 11:40", "programmed": 37829, "forecast": 37909}, {"timestamp": "2009-07-13 11:50", "programmed": 37829, "forecast": 38124}, {"timestamp": "2009-07-13 12:00", "programmed": 38751, "forecast": 38340}, {"timestamp": "2009-07-13 12:10", "programmed": 38751, "forecast": 38544}, {"timestamp": "2009-07-13 12:20", "programmed": 38751, "forecast": 38722}, {"timestamp": "2009-07-13 12:30", "programmed": 38751, "forecast": 38873}, {"timestamp": "2009-07-13 12:40", "programmed": 38751, "forecast": 38999}, {"timestamp": "2009-07-13 12:50", "programmed": 38751, "forecast": 39099}, {"timestamp": "2009-07-13 13:00", "programmed": 39122, "forecast": 39172}, {"timestamp": "2009-07-13 13:10", "programmed": 39122, "forecast": 39204}, {"timestamp": "2009-07-13 13:20", "programmed": 39122, "forecast": 39179}, {"timestamp": "2009-07-13 13:30", "programmed": 39122, "forecast": 39096}, {"timestamp": "2009-07-13 13:40", "programmed": 39122, "forecast": 38957}, {"timestamp": "2009-07-13 13:50", "programmed": 39122, "forecast": 38760}, {"timestamp": "2009-07-13 14:00", "programmed": 38126, "forecast": 38506}, {"timestamp": "2009-07-13 14:10", "programmed": 38126, "forecast": 38243}, {"timestamp": "2009-07-13 14:20", "programmed": 38126, "forecast": 38020}, {"timestamp": "2009-07-13 14:30", "programmed": 38126, "forecast": 37836}, {"timestamp": "2009-07-13 14:40", "programmed": 38126, "forecast": 37691}, {"timestamp": "2009-07-13 14:50", "programmed": 38126, "forecast": 37586}, {"timestamp": "2009-07-13 15:00", "programmed": 37305, "forecast": 37520}, {"timestamp": "2009-07-13 15:10", "programmed": 37305, "forecast": 37486}, {"timestamp": "2009-07-13 15:20", "programmed": 37305, "forecast": 37479}, {"timestamp": "2009-07-13 15:30", "programmed": 37305, "forecast": 37498}, {"timestamp": "2009-07-13 15:40", "programmed": 37305, "forecast": 37542}, {"timestamp": "2009-07-13 15:50", "programmed": 37305, "forecast": 37612}, {"timestamp": "2009-07-13 16:00", "programmed": 37618, "forecast": 37709}, {"timestamp": "2009-07-13 16:10", "programmed": 37618, "forecast": 37803}, {"timestamp": "2009-07-13 16:20", "programmed": 37618, "forecast": 37868}, {"timestamp": "2009-07-13 16:30", "programmed": 37618, "forecast": 37904}, {"timestamp": "2009-07-13 16:40", "programmed": 37618, "forecast": 37911}, {"timestamp": "2009-07-13 16:50", "programmed": 37618, "forecast": 37889}, {"timestamp": "2009-07-13 17:00", "programmed": 37240, "forecast": 37837}, {"timestamp": "2009-07-13 17:10", "programmed": 37240, "forecast": 37764}, {"timestamp": "2009-07-13 17:20", "programmed": 37240, "forecast": 37680}, {"timestamp": "2009-07-13 17:30", "programmed": 37240, "forecast": 37584}, {"timestamp": "2009-07-13 17:40", "programmed": 37240, "forecast": 37477}, {"timestamp": "2009-07-13 17:50", "programmed": 37240, "forecast": 37357}, {"timestamp": "2009-07-13 18:00", "programmed": 36306, "forecast": 37226}, {"timestamp": "2009-07-13 18:10", "programmed": 36306, "forecast": 37070}, {"timestamp": "2009-07-13 18:20", "programmed": 36306, "forecast": 36873}, {"timestamp": "2009-07-13 18:30", "programmed": 36306, "forecast": 36637}, {"timestamp": "2009-07-13 18:40", "programmed": 36306, "forecast": 36360}, {"timestamp": "2009-07-13 18:50", "programmed": 36306, "forecast": 36044}, {"timestamp": "2009-07-13 19:00", "programmed": 35213, "forecast": 35687}, {"timestamp": "2009-07-13 19:10", "programmed": 35213, "forecast": 35335}, {"timestamp": "2009-07-13 19:20", "programmed": 35213, "forecast": 35031}, {"timestamp": "2009-07-13 19:30", "programmed": 35213, "forecast": 34774}, {"timestamp": "2009-07-13 19:40", "programmed": 35213, "forecast": 34565}, {"timestamp": "2009-07-13 19:50", "programmed": 35213, "forecast": 34404}, {"timestamp": "2009-07-13 20:00", "programmed": 34311, "forecast": 34290}, {"timestamp": "2009-07-13 20:10", "programmed": 34311, "forecast": 34203}, {"timestamp": "2009-07-13 20:20", "programmed": 34311, "forecast": 34120}, {"timestamp": "2009-07-13 20:30", "programmed": 34311, "forecast": 34042}, {"timestamp": "2009-07-13 20:40", "programmed": 34311, "forecast": 33969}, {"timestamp": "2009-07-13 20:50", "programmed": 34311, "forecast": 33901}, {"timestamp": "2009-07-13 21:00", "programmed": 33828, "forecast": 33841}, {"timestamp": "2009-07-13 21:10", "programmed": 33828, "forecast": 33798}, {"timestamp": "2009-07-13 21:20", "programmed": 33828, "forecast": 33794}, {"timestamp": "2009-07-13 21:30", "programmed": 33828, "forecast": 33828}, {"timestamp": "2009-07-13 21:40", "programmed": 33828, "forecast": 33902}, {"timestamp": "2009-07-13 21:50", "programmed": 33828, "forecast": 34014}, {"timestamp": "2009-07-13 22:00", "programmed": 34114, "forecast": 34165}, {"timestamp": "2009-07-13 22:10", "programmed": 34114, "forecast": 34273}, {"timestamp": "2009-07-13 22:20", "programmed": 34114, "forecast": 34257}, {"timestamp": "2009-07-13 22:30", "programmed": 34114, "forecast": 34115}, {"timestamp": "2009-07-13 22:40", "programmed": 34114, "forecast": 33849}, {"timestamp": "2009-07-13 22:50", "programmed": 34114, "forecast": 33458}, {"timestamp": "2009-07-13 23:00", "programmed": 31484, "forecast": 32941}, {"timestamp": "2009-07-13 23:10", "programmed": 31484, "forecast": 32378}, {"timestamp": "2009-07-13 23:20", "programmed": 31484, "forecast": 31846}, {"timestamp": "2009-07-13 23:30", "programmed": 31484, "forecast": 31345}, {"timestamp": "2009-07-13 23:40", "programmed": 31484, "forecast": 30875}, {"timestamp": "2009-07-13 23:50", "programmed": 31484, "forecast": 30435}, {"timestamp": "2009-07-14 00:00", "programmed": 28801, "forecast": 30026}, {"timestamp": "2009-07-14 00:10", "programmed": 28801, "forecast": 29633}, {"timestamp": "2009-07-14 00:20", "programmed": 28801, "forecast": 29239}, {"timestamp": "2009-07-14 00:30", "programmed": 28801, "forecast": 28844}, {"timestamp": "2009-07-14 00:40", "programmed": 28801, "forecast": 28447}, {"timestamp": "2009-07-14 00:50", "programmed": 28801, "forecast": 28049}, {"timestamp": "2009-07-14 01:00", "programmed": 26467, "forecast": 27650}, {"timestamp": "2009-07-14 01:10", "programmed": 26467, "forecast": 27263}, {"timestamp": "2009-07-14 01:20", "programmed": 26467, "forecast": 26901}, {"timestamp": "2009-07-14 01:30", "programmed": 26467, "forecast": 26565}, {"timestamp": "2009-07-14 01:40", "programmed": 26467, "forecast": 26254}, {"timestamp": "2009-07-14 01:50", "programmed": 26467, "forecast": 25968}, {"timestamp": "2009-07-14 02:00", "programmed": 25020, "forecast": 25708}, {"timestamp": "2009-07-14 02:10", "programmed": 25020, "forecast": 25477}, {"timestamp": "2009-07-14 02:20", "programmed": 25020, "forecast": 25279}, {"timestamp": "2009-07-14 02:30", "programmed": 25020, "forecast": 25114}, {"timestamp": "2009-07-14 02:40", "programmed": 25020, "forecast": 24982}, {"timestamp": "2009-07-14 02:50", "programmed": 25020, "forecast": 24884}, {"timestamp": "2009-07-14 03:00", "programmed": 24361, "forecast": 24818}, {"timestamp": "2009-07-14 03:10", "programmed": 24361, "forecast": 24766}, {"timestamp": "2009-07-14 03:20", "programmed": 24361, "forecast": 24706}, {"timestamp": "2009-07-14 03:30", "programmed": 24361, "forecast": 24638}, {"timestamp": "2009-07-14 03:40", "programmed": 24361, "forecast": 24563}, {"timestamp": "2009-07-14 03:50", "programmed": 24361, "forecast": 24480}]